windermere/__init__.py
windermere/helper_functions.py
windermere/linear_regression.py
windermere/logistic_regression.py
windermere-0.1.5.dist-info/METADATA
windermere-0.1.5.dist-info/WHEEL
windermere-0.1.5.dist-info/entry_points.txt
windermere-0.1.5.dist-info/RECORD
