Metadata-Version: 2.4
Name: windermere
Version: 0.1.5
Summary: A python package containing machine learning algorithms, implemented as I learn them.
Author-email: Joel Crabbe <joel.crabbe@yahoo.com>
Requires-Python: >=3.12
Requires-Dist: matplotlib>=3.10.5
Requires-Dist: numpy>=2.3.2
